{
  "participantId": 14,
  "studyType": 2,
  "age": 18,
  "gender": "Female",
  "results": [
    {
      "trialIndex": 0,
      "shape": "x",
      "repetition": 1,
      "ratings": {
        "1": 10,
        "2": 8,
        "3": 6,
        "4": 3,
        "5": 0
      },
      "displayOrder": [
        4,
        2,
        3,
        1,
        5
      ],
      "duration": 101.179
    },
    {
      "trialIndex": 1,
      "shape": "y",
      "repetition": 1,
      "ratings": {
        "1": 8,
        "2": 10,
        "3": 6,
        "4": 3,
        "5": 0
      },
      "displayOrder": [
        4,
        5,
        3,
        1,
        2
      ],
      "duration": 23.126
    },
    {
      "trialIndex": 2,
      "shape": "a",
      "repetition": 1,
      "ratings": {
        "1": 7,
        "2": 9,
        "3": 5,
        "4": 3,
        "5": 0
      },
      "displayOrder": [
        3,
        4,
        5,
        1,
        2
      ],
      "duration": 31.999
    },
    {
      "trialIndex": 3,
      "shape": "e",
      "repetition": 1,
      "ratings": {
        "1": 5,
        "2": 10,
        "3": 8,
        "4": 3,
        "5": 0
      },
      "displayOrder": [
        4,
        1,
        3,
        2,
        5
      ],
      "duration": 20.161
    },
    {
      "trialIndex": 4,
      "shape": "s",
      "repetition": 1,
      "ratings": {
        "1": 10,
        "2": 8,
        "3": 8,
        "4": 2,
        "5": 0
      },
      "displayOrder": [
        1,
        5,
        2,
        3,
        4
      ],
      "duration": 21.698
    },
    {
      "trialIndex": 5,
      "shape": "a",
      "repetition": 2,
      "ratings": {
        "1": 10,
        "2": 10,
        "3": 7,
        "4": 2,
        "5": 0
      },
      "displayOrder": [
        1,
        5,
        3,
        2,
        4
      ],
      "duration": 22.666
    },
    {
      "trialIndex": 6,
      "shape": "e",
      "repetition": 2,
      "ratings": {
        "1": 8,
        "2": 8,
        "3": 10,
        "4": 6,
        "5": 0
      },
      "displayOrder": [
        1,
        5,
        2,
        4,
        3
      ],
      "duration": 20.799
    },
    {
      "trialIndex": 7,
      "shape": "s",
      "repetition": 2,
      "ratings": {
        "1": 10,
        "2": 7,
        "3": 10,
        "4": 3,
        "5": 0
      },
      "displayOrder": [
        4,
        1,
        2,
        3,
        5
      ],
      "duration": 19.532
    },
    {
      "trialIndex": 8,
      "shape": "a",
      "repetition": 3,
      "ratings": {
        "1": 10,
        "2": 5,
        "3": 6,
        "4": 3,
        "5": 0
      },
      "displayOrder": [
        5,
        4,
        2,
        3,
        1
      ],
      "duration": 17.198
    },
    {
      "trialIndex": 9,
      "shape": "e",
      "repetition": 3,
      "ratings": {
        "1": 5,
        "2": 10,
        "3": 8,
        "4": 3,
        "5": 0
      },
      "displayOrder": [
        4,
        1,
        5,
        2,
        3
      ],
      "duration": 16.799
    },
    {
      "trialIndex": 10,
      "shape": "s",
      "repetition": 3,
      "ratings": {
        "1": 10,
        "2": 10,
        "3": 7,
        "4": 3,
        "5": 0
      },
      "displayOrder": [
        3,
        1,
        4,
        2,
        5
      ],
      "duration": 17.132
    }
  ],
  "postQuestions": {
    "q1": "There was shifting in the lines that formed each of the shapes, where the shape would deform, then return to the high-quality version repeatedly."
  }
}